lazyllm/__init__.py
lazyllm/cli/__init__.py
lazyllm/cli/deploy.py
lazyllm/cli/install.py
lazyllm/cli/main.py
lazyllm/cli/run.py
lazyllm/client.py
lazyllm/common/__init__.py
lazyllm/common/common.py
lazyllm/common/deprecated.py
lazyllm/common/globals.py
lazyllm/common/logger.py
lazyllm/common/multiprocessing.py
lazyllm/common/option.py
lazyllm/common/queue.py
lazyllm/common/registry.py
lazyllm/common/threading.py
lazyllm/common/utils.py
lazyllm/components/__init__.py
lazyllm/components/auto/__init__.py
lazyllm/components/auto/auto_helper.py
lazyllm/components/auto/autodeploy.py
lazyllm/components/auto/autofinetune.py
lazyllm/components/auto/configure/__init__.py
lazyllm/components/auto/configure/core/__init__.py
lazyllm/components/auto/configure/core/configs/deploy.csv
lazyllm/components/auto/configure/core/configs/finetune.csv
lazyllm/components/auto/configure/core/configuration.py
lazyllm/components/auto/configure/core/protocol.py
lazyllm/components/auto/configure/core/rule.py
lazyllm/components/auto/configure/scripts/database_test.py
lazyllm/components/auto/configure/scripts/generate_test.py
lazyllm/components/auto/configure/scripts/rule_test.py
lazyllm/components/auto/configure/scripts/sample_deploy.csv
lazyllm/components/auto/configure/scripts/sample_finetune.csv
lazyllm/components/auto/dependencies/__init__.py
lazyllm/components/auto/dependencies/modelsconfig.py
lazyllm/components/auto/dependencies/requirements.py
lazyllm/components/core.py
lazyllm/components/data.py
lazyllm/components/deploy/__init__.py
lazyllm/components/deploy/base.py
lazyllm/components/deploy/lightllm.py
lazyllm/components/deploy/lmdeploy/chat_template.json
lazyllm/components/deploy/lmdeploy.py
lazyllm/components/deploy/relay/__init__.py
lazyllm/components/deploy/relay/base.py
lazyllm/components/deploy/relay/server.py
lazyllm/components/deploy/vllm.py
lazyllm/components/embedding/__init__.py
lazyllm/components/embedding/embed.py
lazyllm/components/finetune/__init__.py
lazyllm_beta-0.0.1.dist-info/LICENSE
lazyllm_beta-0.0.1.dist-info/METADATA
lazyllm_beta-0.0.1.dist-info/WHEEL
lazyllm_beta-0.0.1.dist-info/entry_points.txt
lazyllm_beta-0.0.1.dist-info/RECORD
