Metadata-Version: 2.1
Name: lazyllm-beta
Version: 0.0.1
Summary: A Low-code Development Tool For Building Multi-agent LLMs Applications.
License: Apache-2.0 license
Author: wangzhihong
Author-email: wangzhihong@sensetime.com
Requires-Python: >=3.10,<4.0
Classifier: License :: Other/Proprietary License
Classifier: Programming Language :: Python :: 3
Classifier: Programming Language :: Python :: 3.10
Classifier: Programming Language :: Python :: 3.11
Classifier: Programming Language :: Python :: 3.12
Provides-Extra: full
Provides-Extra: standard
Requires-Dist: appdirs
Requires-Dist: bm25s (>=0.1.10,<0.2.0)
Requires-Dist: chattts (>=0.1.1,<0.2.0) ; extra == "standard" or extra == "full"
Requires-Dist: chromadb (>=0.5.5,<0.6.0)
Requires-Dist: cloudpickle (>=3.0.0)
Requires-Dist: collie-lm (>=1.0.7) ; extra == "full"
Requires-Dist: datasets (>=2.18.0) ; extra == "standard" or extra == "full"
Requires-Dist: deepspeed (>=0.12.3) ; extra == "standard" or extra == "full"
Requires-Dist: diffusers (>=0.30.0,<0.31.0) ; extra == "standard" or extra == "full"
Requires-Dist: docstring-parser (>=0.16,<0.17)
Requires-Dist: faiss-cpu (>=1.8.0) ; extra == "standard" or extra == "full"
Requires-Dist: fastapi (>=0.111.0)
Requires-Dist: fire (>=0.6.0) ; extra == "standard" or extra == "full"
Requires-Dist: flake8 (>=7.0.0)
Requires-Dist: flash-attn (>=2.6.3,<3.0.0) ; extra == "full"
Requires-Dist: funasr (>=1.1.4,<2.0.0) ; extra == "standard" or extra == "full"
Requires-Dist: google (>=3.0.0) ; extra == "standard" or extra == "full"
Requires-Dist: gradio (>=3.48.0)
Requires-Dist: gradio-client (>=0.6.1)
Requires-Dist: huggingface-hub (>=0.23.1) ; extra == "full"
Requires-Dist: jieba (>=0.42.1)
Requires-Dist: json5 (>=0.9.25,<0.10.0)
Requires-Dist: lazyllm-llamafactory (>=0.8.3.dev0,<0.9.0) ; extra == "standard" or extra == "full"
Requires-Dist: lightllm (>=0.0.1,<0.0.2) ; extra == "full"
Requires-Dist: llama-index (>=0.10.25) ; extra == "standard" or extra == "full"
Requires-Dist: llama-index-core (>=0.11.2,<0.12.0)
Requires-Dist: llama-index-embeddings-huggingface (>=0.2.0) ; extra == "standard" or extra == "full"
Requires-Dist: llama-index-retrievers-bm25 (>=0.1.3) ; extra == "full"
Requires-Dist: llama-index-storage-docstore-redis (>=0.1.2) ; extra == "full"
Requires-Dist: llama-index-storage-index-store-redis (>=0.1.2) ; extra == "full"
Requires-Dist: llama-index-storage-kvstore-redis (>=0.1.5) ; extra == "full"
Requires-Dist: llama-index-vector-stores-redis (>=0.2.0) ; extra == "full"
Requires-Dist: lmdeploy (>=0.5.3,<0.6.0) ; extra == "standard" or extra == "full"
Requires-Dist: loguru (>=0.7.2)
Requires-Dist: loralib
Requires-Dist: modelscope (>=1.14.0) ; extra == "standard" or extra == "full"
Requires-Dist: nltk (>=3.8.1,<4.0.0)
Requires-Dist: numpy (>=1.26.4) ; extra == "standard" or extra == "full"
Requires-Dist: pandas (>=2.2.2) ; extra == "standard" or extra == "full"
Requires-Dist: peft (>=0.3.0) ; extra == "standard" or extra == "full"
Requires-Dist: protobuf (>=3.20.1)
Requires-Dist: pydantic (>=2.5.0)
Requires-Dist: pyjwt (>=2.8.0)
Requires-Dist: pystemmer (>=2.2.0.1,<3.0.0.0)
Requires-Dist: rank-bm25 (>=0.2.2) ; extra == "standard" or extra == "full"
Requires-Dist: redis (>=5.0.4) ; extra == "full"
Requires-Dist: redisvl (>=0.1.3) ; extra == "full"
Requires-Dist: requests (>=2.32.2)
Requires-Dist: scikit-learn (>=1.5.0) ; extra == "standard" or extra == "full"
Requires-Dist: setuptools (<70.0.0)
Requires-Dist: sortedcontainers (>=2.4.0,<3.0.0) ; extra == "full"
Requires-Dist: spacy (>=3.7.5,<4.0.0)
Requires-Dist: tensorboard (>=2.16.2) ; extra == "full"
Requires-Dist: tensorboard-data-server (>=0.7.2) ; extra == "full"
Requires-Dist: tiktoken (>=0.7.0,<0.8.0)
Requires-Dist: timm (>=1.0.8,<2.0.0) ; extra == "standard" or extra == "full"
Requires-Dist: toml
Requires-Dist: torch (>=2.1.2) ; extra == "standard" or extra == "full"
Requires-Dist: torchvision (>=0.16.2) ; extra == "standard" or extra == "full"
Requires-Dist: transformers (>=4.41.1) ; extra == "standard" or extra == "full"
Requires-Dist: uvicorn (<0.29.0)
Requires-Dist: vllm (==0.5.0) ; extra == "standard" or extra == "full"
Requires-Dist: wandb (>=0.17.0) ; extra == "standard" or extra == "full"
